fief_client/__init__.py
fief_client/client.py
fief_client/crypto.py
fief_client/pkce.py
fief_client/py.typed
fief_client/integrations/__init__.py
fief_client/integrations/cli.py
fief_client/integrations/fastapi.py
fief_client/integrations/flask.py
fief_client-0.18.6.dist-info/METADATA
fief_client-0.18.6.dist-info/WHEEL
fief_client-0.18.6.dist-info/licenses/LICENSE
fief_client-0.18.6.dist-info/RECORD
